jsrm/__init__.py
jsrm/integration.py
jsrm/math_utils.py
jsrm/parameters/__init__.py
jsrm/parameters/hsa_params.py
jsrm/rendering/__init__.py
jsrm/rendering/planar_hsa/opencv_renderer.py
jsrm/symbolic_derivation/__init__.py
jsrm/symbolic_derivation/pendulum.py
jsrm/symbolic_derivation/planar_hsa.py
jsrm/symbolic_derivation/planar_pcs.py
jsrm/symbolic_derivation/symbolic_utils.py
jsrm/symbolic_expressions/pendulum_nl-1.dill
jsrm/symbolic_expressions/pendulum_nl-2.dill
jsrm/symbolic_expressions/pendulum_nl-3.dill
jsrm/symbolic_expressions/planar_hsa_ns-1_nrs-2.dill
jsrm/symbolic_expressions/planar_hsa_ns-1_nrs-4.dill
jsrm/symbolic_expressions/planar_pcs_ns-1.dill
jsrm/symbolic_expressions/planar_pcs_ns-2.dill
jsrm/symbolic_expressions/planar_pcs_ns-3.dill
jsrm/symbolic_expressions/planar_pcs_ns-4.dill
jsrm/symbolic_expressions/planar_pcs_ns-5.dill
jsrm/systems/__init__.py
jsrm/systems/euler_lagrangian.py
jsrm/systems/pcs.py
jsrm/systems/pendulum.py
jsrm/systems/planar_hsa.py
jsrm/systems/planar_pcs.py
jsrm/systems/planar_pcs_sym.py
jsrm/systems/pneumatically_actuated_planar_pcs.py
jsrm/systems/tendon_actuated_planar_pcs.py
jsrm/systems/utils.py
jsrm/utils/__init__.py
jsrm/utils/lie_algebra.py
jsrm/utils/numerical_jacobian.py
jsrm/utils/tolerance.py
jsrm-0.1.0.dist-info/licenses/LICENSE.txt
jsrm-0.1.0.dist-info/METADATA
jsrm-0.1.0.dist-info/WHEEL
jsrm-0.1.0.dist-info/top_level.txt
jsrm-0.1.0.dist-info/RECORD
