Metadata-Version: 2.4
Name: jsrm
Version: 0.1.0
Summary: Kinematic and dynamic models of continuum and articulated soft robots.
Author-email: Maximilian Stölzle <maximilian@stoelzle.ch>, Solange Gribonval <solange.gribonval@polytechnique.edu>
Maintainer-email: Maximilian Stölzle <maximilian@stoelzle.ch>
License: Copyright (c) 2016 The Python Packaging Authority (PyPA)
Project-URL: Homepage, https://github.com/tud-cor-sr/jax-soft-robot-modelling
Project-URL: Bug Reports, https://github.com/tud-cor-sr/jax-soft-robot-modelling/issues
Project-URL: Source, https://github.com/tud-cor-sr/jax-soft-robot-modelling
Keywords: JAX,Soft Robotics,Kinematics,Dynamics
Classifier: Development Status :: 3 - Alpha
Classifier: Intended Audience :: Developers
Classifier: Topic :: Software Development :: Build Tools
Classifier: License :: OSI Approved :: MIT License
Classifier: Programming Language :: Python :: 3
Classifier: Programming Language :: Python :: 3.10
Classifier: Programming Language :: Python :: 3.11
Classifier: Programming Language :: Python :: 3.12
Classifier: Programming Language :: Python :: 3.13
Classifier: Programming Language :: Python :: 3 :: Only
Requires-Python: >=3.10
License-File: LICENSE.txt
Requires-Dist: dill
Requires-Dist: jax
Requires-Dist: numpy
Requires-Dist: quadax
Requires-Dist: equinox
Requires-Dist: peppercorn
Requires-Dist: sympy>=1.11
Provides-Extra: dev
Requires-Dist: bump2version; extra == "dev"
Requires-Dist: check-manifest; extra == "dev"
Requires-Dist: codecov; extra == "dev"
Requires-Dist: coverage; extra == "dev"
Requires-Dist: pre-commit; extra == "dev"
Requires-Dist: pytest; extra == "dev"
Requires-Dist: pytest-cov; extra == "dev"
Requires-Dist: pytest-html; extra == "dev"
Requires-Dist: ruff; extra == "dev"
Requires-Dist: tox; extra == "dev"
Provides-Extra: examples
Requires-Dist: diffrax; extra == "examples"
Requires-Dist: jaxopt; extra == "examples"
Requires-Dist: matplotlib; extra == "examples"
Requires-Dist: opencv-python; extra == "examples"
Requires-Dist: scipy; extra == "examples"
Provides-Extra: test
Requires-Dist: codecov; extra == "test"
Requires-Dist: coverage; extra == "test"
Requires-Dist: pytest; extra == "test"
Requires-Dist: pytest-cov; extra == "test"
Requires-Dist: pytest-html; extra == "test"
Requires-Dist: tox; extra == "test"
Dynamic: license-file
